octobot_commons/__init__.pxd
octobot_commons/__init__.py
octobot_commons/aiohttp_util.py
octobot_commons/async_job.cpython-38-darwin.so
octobot_commons/async_job.pxd
octobot_commons/async_job.py
octobot_commons/asyncio_tools.py
octobot_commons/authentication.py
octobot_commons/channels_name.py
octobot_commons/constants.py
octobot_commons/data_util.cpython-38-darwin.so
octobot_commons/data_util.pxd
octobot_commons/data_util.py
octobot_commons/dict_util.py
octobot_commons/enums.py
octobot_commons/errors.py
octobot_commons/evaluator_util.pxd
octobot_commons/evaluators_util.cpython-38-darwin.so
octobot_commons/evaluators_util.py
octobot_commons/external_resources_manager.py
octobot_commons/json_util.py
octobot_commons/list_util.cpython-38-darwin.so
octobot_commons/list_util.pxd
octobot_commons/list_util.py
octobot_commons/logical_operators.py
octobot_commons/multiprocessing_util.py
octobot_commons/number_util.py
octobot_commons/optimization_campaign.py
octobot_commons/os_clock_sync.py
octobot_commons/os_util.py
octobot_commons/pretty_printer.cpython-38-darwin.so
octobot_commons/pretty_printer.pxd
octobot_commons/pretty_printer.py
octobot_commons/support.py
octobot_commons/system_resources_watcher.py
octobot_commons/thread_util.py
octobot_commons/time_frame_manager.cpython-38-darwin.so
octobot_commons/time_frame_manager.pxd
octobot_commons/time_frame_manager.py
octobot_commons/timestamp_util.py
octobot_commons/configuration/__init__.py
octobot_commons/configuration/config_file_manager.py
octobot_commons/configuration/config_operations.py
octobot_commons/configuration/configuration.py
octobot_commons/configuration/fields_utils.py
octobot_commons/configuration/user_input_configuration.py
octobot_commons/configuration/user_inputs.py
octobot_commons/databases/__init__.pxd
octobot_commons/databases/__init__.py
octobot_commons/databases/cache_client.py
octobot_commons/databases/cache_manager.py
octobot_commons/databases/bases/__init__.py
OctoBot_Commons-1.8.28.dist-info/LICENSE
OctoBot_Commons-1.8.28.dist-info/METADATA
OctoBot_Commons-1.8.28.dist-info/WHEEL
OctoBot_Commons-1.8.28.dist-info/top_level.txt
OctoBot_Commons-1.8.28.dist-info/RECORD
