Metadata-Version: 2.1
Name: OctoBot-Commons
Version: 1.8.28
Summary: OctoBot project common modules
Home-page: https://github.com/Drakkar-Software/OctoBot-Commons
Author: Drakkar-Software
Author-email: drakkar-software@protonmail.com
License: LGPL-3.0
Platform: UNKNOWN
Classifier: Development Status :: 5 - Production/Stable
Classifier: Operating System :: OS Independent
Classifier: Operating System :: MacOS :: MacOS X
Classifier: Operating System :: Microsoft :: Windows
Classifier: Operating System :: POSIX
Classifier: Programming Language :: Python :: 3.8
Classifier: Programming Language :: Python :: 3.9
Requires-Python: >=3.8
Requires-Dist: cython (==0.29.32)
Requires-Dist: numpy (==1.24.0)
Requires-Dist: jsonschema (==3.2.0)
Requires-Dist: cryptography
Requires-Dist: sortedcontainers
Requires-Dist: requests
Requires-Dist: psutil (==5.9.4)
Requires-Dist: aiosqlite (<0.17,>=0.16.0)
